[{"_id":{"timestamp":1469855734,"machineIdentifier":1136930,"processIdentifier":9999,"counter":12750589},"id":381949397,"name":"Anurag Thakur","screenName":"ianuragthakur","location":"Delhi/HP","description":"Member of Parliament (LS), President-BCCI, President BJP\u0027s Youth Wing (BJYM) \u0026 Chairman-Parliamentary Standing Committee on IT Links/RTs not an endorsement.","descriptionURLEntities":[],"isContributorsEnabled":false,"profileImageUrl":"http://pbs.twimg.com/profile_images/747340457705766912/cyZNEHK4_normal.jpg","profileImageUrlHttps":"https://pbs.twimg.com/profile_images/747340457705766912/cyZNEHK4_normal.jpg","isDefaultProfileImage":false,"url":"http://www.anuragthakur.in","isProtected":false,"followersCount":530264,"profileBackgroundColor":"EDECE9","profileTextColor":"634047","profileLinkColor":"088253","profileSidebarFillColor":"E3E2DE","profileSidebarBorderColor":"FFFFFF","profileUseBackgroundImage":true,"isDefaultProfile":false,"showAllInlineMedia":false,"friendsCount":154,"createdAt":"Sep 29, 2011 12:59:37 PM","favouritesCount":0,"utcOffset":19800,"timeZone":"New Delhi","profileBackgroundImageUrl":"http://abs.twimg.com/images/themes/theme3/bg.gif","profileBackgroundImageUrlHttps":"https://abs.twimg.com/images/themes/theme3/bg.gif","profileBannerImageUrl":"https://pbs.twimg.com/profile_banners/381949397/1466513431","profileBackgroundTiled":false,"lang":"en","statusesCount":8732,"isGeoEnabled":false,"isVerified":true,"translator":false,"listedCount":580,"isFollowRequestSent":false},{"_id":{"timestamp":1469855734,"machineIdentifier":1136930,"processIdentifier":9999,"counter":12750594},"id":513438857,"name":"Boston Bobblehead","screenName":"DBloom451","description":"Independent Conservative, after GOP Amnesty betrayal, and Yuge BoSox \u0026 USC football fan. MPP/MBA @USC. I Don\u0027t Read DMs, so please don\u0027t send.","descriptionURLEntities":[],"isContributorsEnabled":false,"profileImageUrl":"http://pbs.twimg.com/profile_images/684190701979066369/aZEsk75X_normal.jpg","profileImageUrlHttps":"https://pbs.twimg.com/profile_images/684190701979066369/aZEsk75X_normal.jpg","isDefaultProfileImage":false,"isProtected":false,"followersCount":10084,"profileBackgroundColor":"C0DEED","profileTextColor":"000000","profileLinkColor":"0084B4","profileSidebarFillColor":"000000","profileSidebarBorderColor":"000000","profileUseBackgroundImage":true,"isDefaultProfile":false,"showAllInlineMedia":false,"friendsCount":7591,"createdAt":"Mar 4, 2012 12:13:33 AM","favouritesCount":4320,"utcOffset":-10800,"timeZone":"Atlantic Time (Canada)","profileBackgroundImageUrl":"http://pbs.twimg.com/profile_background_images/707869116913295360/1Wln2AyU.jpg","profileBackgroundImageUrlHttps":"https://pbs.twimg.com/profile_background_images/707869116913295360/1Wln2AyU.jpg","profileBannerImageUrl":"https://pbs.twimg.com/profile_banners/513438857/1458250894","profileBackgroundTiled":true,"lang":"en","statusesCount":16288,"isGeoEnabled":false,"isVerified":false,"translator":false,"listedCount":85,"isFollowRequestSent":false},{"_id":{"timestamp":1469855734,"machineIdentifier":1136930,"processIdentifier":9999,"counter":12750596},"id":457812556,"name":"Mohamed Abdi","screenName":"JournoMoA","location":"international ","description":"Freelance Journalist covering International Terrorism.","descriptionURLEntities":[],"isContributorsEnabled":false,"profileImageUrl":"http://pbs.twimg.com/profile_images/700318147858075652/vFayre2O_normal.jpg","profileImageUrlHttps":"https://pbs.twimg.com/profile_images/700318147858075652/vFayre2O_normal.jpg","isDefaultProfileImage":false,"isProtected":false,"followersCount":14686,"profileBackgroundColor":"C0DEED","profileTextColor":"333333","profileLinkColor":"0084B4","profileSidebarFillColor":"DDEEF6","profileSidebarBorderColor":"C0DEED","profileUseBackgroundImage":true,"isDefaultProfile":true,"showAllInlineMedia":false,"friendsCount":210,"createdAt":"Jan 8, 2012 3:11:38 AM","favouritesCount":62,"utcOffset":-1,"profileBackgroundImageUrl":"http://abs.twimg.com/images/themes/theme1/bg.png","profileBackgroundImageUrlHttps":"https://abs.twimg.com/images/themes/theme1/bg.png","profileBackgroundTiled":false,"lang":"en","statusesCount":124,"isGeoEnabled":false,"isVerified":false,"translator":false,"listedCount":199,"isFollowRequestSent":false},{"_id":{"timestamp":1469855734,"machineIdentifier":1136930,"processIdentifier":9999,"counter":12750598},"id":5392522,"name":"NPR","screenName":"NPR","location":"Washington, DC","description":"News. Arts \u0026 Life. Music. Everything and more from NPR.","descriptionURLEntities":[],"isContributorsEnabled":false,"profileImageUrl":"http://pbs.twimg.com/profile_images/722199003845304320/s2zwEoao_normal.jpg","profileImageUrlHttps":"https://pbs.twimg.com/profile_images/722199003845304320/s2zwEoao_normal.jpg","isDefaultProfileImage":false,"url":"http://www.npr.org","isProtected":false,"followersCount":5982467,"profileBackgroundColor":"9AE4E8","profileTextColor":"000000","profileLinkColor":"0000FF","profileSidebarFillColor":"E0FF92","profileSidebarBorderColor":"87BC44","profileUseBackgroundImage":true,"isDefaultProfile":false,"showAllInlineMedia":false,"friendsCount":73154,"createdAt":"Apr 22, 2007 11:10:15 AM","favouritesCount":1781,"utcOffset":-14400,"timeZone":"Eastern Time (US \u0026 Canada)","profileBackgroundImageUrl":"http://pbs.twimg.com/profile_background_images/414161733/nprnews_background.jpg","profileBackgroundImageUrlHttps":"https://pbs.twimg.com/profile_background_images/414161733/nprnews_background.jpg","profileBannerImageUrl":"https://pbs.twimg.com/profile_banners/5392522/1406560384","profileBackgroundTiled":false,"lang":"en","statusesCount":96605,"isGeoEnabled":false,"isVerified":true,"translator":false,"listedCount":60292,"isFollowRequestSent":false},{"_id":{"timestamp":1469855734,"machineIdentifier":1136930,"processIdentifier":9999,"counter":12750599},"id":30699754,"name":"Rukmini Callimachi","screenName":"rcallimachi","location":"New York, New York","description":"Correspondent for The New York Times, focusing on al-Qaeda and ISIS. Previously, seven years in West Africa as correspondent \u0026 bureau chief for The AP.","descriptionURLEntities":[],"isContributorsEnabled":false,"profileImageUrl":"http://pbs.twimg.com/profile_images/537328382682222593/SI_oJZM8_normal.jpeg","profileImageUrlHttps":"https://pbs.twimg.com/profile_images/537328382682222593/SI_oJZM8_normal.jpeg","isDefaultProfileImage":false,"url":"http://topics.nytimes.com/top/reference/timestopics/people/c/rukmini_callimachi/index.html","isProtected":false,"followersCount":81293,"profileBackgroundColor":"C0DEED","profileTextColor":"333333","profileLinkColor":"0084B4","profileSidebarFillColor":"DDEEF6","profileSidebarBorderColor":"C0DEED","profileUseBackgroundImage":true,"isDefaultProfile":true,"showAllInlineMedia":false,"friendsCount":2593,"createdAt":"Apr 13, 2009 12:58:23 AM","favouritesCount":8846,"utcOffset":10800,"timeZone":"Athens","profileBackgroundImageUrl":"http://abs.twimg.com/images/themes/theme1/bg.png","profileBackgroundImageUrlHttps":"https://abs.twimg.com/images/themes/theme1/bg.png","profileBannerImageUrl":"https://pbs.twimg.com/profile_banners/30699754/1424660497","profileBackgroundTiled":false,"lang":"en","statusesCount":18962,"isGeoEnabled":false,"isVerified":true,"translator":false,"listedCount":2113,"isFollowRequestSent":false},{"_id":{"timestamp":1469855734,"machineIdentifier":1136930,"processIdentifier":9999,"counter":12750600},"id":1097218164,"name":"Tapan Ghosh","screenName":"hstapanghosh","description":"Uncompromising Hindu activist of Bengal.                              Determined to fight against Islamic aggression \u0026 expansion.","descriptionURLEntities":[],"isContributorsEnabled":false,"profileImageUrl":"http://pbs.twimg.com/profile_images/648358452830474240/0u9l4tUO_normal.jpg","profileImageUrlHttps":"https://pbs.twimg.com/profile_images/648358452830474240/0u9l4tUO_normal.jpg","isDefaultProfileImage":false,"url":"http://hindusamhati.org","isProtected":false,"followersCount":21651,"profileBackgroundColor":"0099B9","profileTextColor":"3C3940","profileLinkColor":"0099B9","profileSidebarFillColor":"95E8EC","profileSidebarBorderColor":"FFFFFF","profileUseBackgroundImage":true,"isDefaultProfile":false,"showAllInlineMedia":false,"friendsCount":139,"createdAt":"Jan 17, 2013 10:58:42 AM","favouritesCount":4128,"utcOffset":19800,"timeZone":"Kolkata","profileBackgroundImageUrl":"http://pbs.twimg.com/profile_background_images/378800000157717351/DhGaFYVO.jpeg","profileBackgroundImageUrlHttps":"https://pbs.twimg.com/profile_background_images/378800000157717351/DhGaFYVO.jpeg","profileBannerImageUrl":"https://pbs.twimg.com/profile_banners/1097218164/1463061229","profileBackgroundTiled":false,"lang":"en","statusesCount":14277,"isGeoEnabled":true,"isVerified":false,"translator":false,"listedCount":145,"isFollowRequestSent":false},{"_id":{"timestamp":1469855734,"machineIdentifier":1136930,"processIdentifier":9999,"counter":12750601},"id":53313935,"name":"Tehseen Poonawalla","screenName":"tehseenp","location":"Delhi-Pune-Mumbai","description":"Political Trendwatcher, Life coach, Entrepreneur \u0026 Columnist. Student of Mythology yet an atheist.","descriptionURLEntities":[],"isContributorsEnabled":false,"profileImageUrl":"http://pbs.twimg.com/profile_images/512661884684603392/f9OKcuLz_normal.jpeg","profileImageUrlHttps":"https://pbs.twimg.com/profile_images/512661884684603392/f9OKcuLz_normal.jpeg","isDefaultProfileImage":false,"isProtected":false,"followersCount":63826,"profileBackgroundColor":"000000","profileTextColor":"333333","profileLinkColor":"0084B4","profileSidebarFillColor":"DDEEF6","profileSidebarBorderColor":"FFFFFF","profileUseBackgroundImage":true,"isDefaultProfile":false,"showAllInlineMedia":false,"friendsCount":9858,"createdAt":"Jul 3, 2009 1:25:04 PM","favouritesCount":6823,"utcOffset":19800,"timeZone":"New Delhi","profileBackgroundImageUrl":"http://pbs.twimg.com/profile_background_images/788283173/6564ac17ede2d25be8d2f0f9511162f9.jpeg","profileBackgroundImageUrlHttps":"https://pbs.twimg.com/profile_background_images/788283173/6564ac17ede2d25be8d2f0f9511162f9.jpeg","profileBannerImageUrl":"https://pbs.twimg.com/profile_banners/53313935/1360610451","profileBackgroundTiled":false,"lang":"en","statusesCount":21758,"isGeoEnabled":false,"isVerified":false,"translator":false,"listedCount":160,"isFollowRequestSent":false},{"_id":{"timestamp":1469855734,"machineIdentifier":1136930,"processIdentifier":9999,"counter":12750603},"id":137804302,"name":"flowered_","screenName":"AmnaaaKhannn","location":"Manchester","description":"disgrace to the community, doing management @ UoM","descriptionURLEntities":[],"isContributorsEnabled":false,"profileImageUrl":"http://pbs.twimg.com/profile_images/739264907720429568/IshDmSkP_normal.jpg","profileImageUrlHttps":"https://pbs.twimg.com/profile_images/739264907720429568/IshDmSkP_normal.jpg","isDefaultProfileImage":false,"url":"https://www.islamichelp.org.uk/ihelp-give/ihelpcaramnakhan/","isProtected":false,"followersCount":4953,"profileBackgroundColor":"000000","profileTextColor":"000000","profileLinkColor":"94D487","profileSidebarFillColor":"000000","profileSidebarBorderColor":"000000","profileUseBackgroundImage":false,"isDefaultProfile":false,"showAllInlineMedia":false,"friendsCount":2678,"createdAt":"Apr 28, 2010 2:30:47 AM","favouritesCount":44989,"utcOffset":3600,"timeZone":"London","profileBackgroundImageUrl":"http://abs.twimg.com/images/themes/theme3/bg.gif","profileBackgroundImageUrlHttps":"https://abs.twimg.com/images/themes/theme3/bg.gif","profileBannerImageUrl":"https://pbs.twimg.com/profile_banners/137804302/1458479189","profileBackgroundTiled":false,"lang":"en","statusesCount":87722,"isGeoEnabled":true,"isVerified":false,"translator":false,"listedCount":25,"isFollowRequestSent":false},{"_id":{"timestamp":1469855734,"machineIdentifier":1136930,"processIdentifier":9999,"counter":12750604},"id":26893155,"name":"Univers Harry Potter","screenName":"UHP","location":"France","description":"French site about Harry Potter : News, Updates and More!","descriptionURLEntities":[],"isContributorsEnabled":false,"profileImageUrl":"http://pbs.twimg.com/profile_images/579999495087374336/1RIZuTDu_normal.png","profileImageUrlHttps":"https://pbs.twimg.com/profile_images/579999495087374336/1RIZuTDu_normal.png","isDefaultProfileImage":false,"url":"http://www.universharrypotter.com","isProtected":false,"followersCount":21569,"profileBackgroundColor":"000000","profileTextColor":"3D1957","profileLinkColor":"7B6801","profileSidebarFillColor":"7AC3EE","profileSidebarBorderColor":"000000","profileUseBackgroundImage":true,"isDefaultProfile":false,"showAllInlineMedia":false,"friendsCount":325,"createdAt":"Mar 27, 2009 5:55:00 AM","favouritesCount":186,"utcOffset":7200,"timeZone":"Paris","profileBackgroundImageUrl":"http://pbs.twimg.com/profile_background_images/378800000120098228/460dae4e03d31b7515acef2c785fd606.png","profileBackgroundImageUrlHttps":"https://pbs.twimg.com/profile_background_images/378800000120098228/460dae4e03d31b7515acef2c785fd606.png","profileBannerImageUrl":"https://pbs.twimg.com/profile_banners/26893155/1427117601","profileBackgroundTiled":true,"lang":"fr","statusesCount":9065,"isGeoEnabled":false,"isVerified":false,"translator":false,"listedCount":221,"isFollowRequestSent":false},{"_id":{"timestamp":1469855734,"machineIdentifier":1136930,"processIdentifier":9999,"counter":12750605},"id":46704429,"name":"Praveen Swami","screenName":"praveenswami","location":"New Delhi","description":"Editor, Strategic Affairs, The Indian Express, and Feared Master of a Ferocious Attack Beagle. Low tolerance for cretins.","descriptionURLEntities":[],"isContributorsEnabled":false,"profileImageUrl":"http://pbs.twimg.com/profile_images/596958928417619968/wVpf-5RS_normal.jpg","profileImageUrlHttps":"https://pbs.twimg.com/profile_images/596958928417619968/wVpf-5RS_normal.jpg","isDefaultProfileImage":false,"url":"http://indianexpress.com/profile/author/praveen-swami/","isProtected":false,"followersCount":57039,"profileBackgroundColor":"C0DEED","profileTextColor":"333333","profileLinkColor":"0084B4","profileSidebarFillColor":"DDEEF6","profileSidebarBorderColor":"C0DEED","profileUseBackgroundImage":true,"isDefaultProfile":true,"showAllInlineMedia":false,"friendsCount":145,"createdAt":"Jun 12, 2009 11:44:38 PM","favouritesCount":610,"utcOffset":19800,"timeZone":"New Delhi","profileBackgroundImageUrl":"http://abs.twimg.com/images/themes/theme1/bg.png","profileBackgroundImageUrlHttps":"https://abs.twimg.com/images/themes/theme1/bg.png","profileBackgroundTiled":false,"lang":"en","statusesCount":17508,"isGeoEnabled":true,"isVerified":true,"translator":false,"listedCount":921,"isFollowRequestSent":false},{"_id":{"timestamp":1469855734,"machineIdentifier":1136930,"processIdentifier":9999,"counter":12750607},"id":20433284,"name":"Eyewitness News","screenName":"ewnupdates","location":"South Africa","description":"INSIDE THE TRUTH","descriptionURLEntities":[],"isContributorsEnabled":false,"profileImageUrl":"http://pbs.twimg.com/profile_images/528193258321498112/7LRNhYBc_normal.png","profileImageUrlHttps":"https://pbs.twimg.com/profile_images/528193258321498112/7LRNhYBc_normal.png","isDefaultProfileImage":false,"url":"http://www.ewn.co.za","isProtected":false,"followersCount":595443,"profileBackgroundColor":"FBFCFC","profileTextColor":"333333","profileLinkColor":"B40000","profileSidebarFillColor":"D2D7DC","profileSidebarBorderColor":"FFFFFF","profileUseBackgroundImage":false,"isDefaultProfile":false,"showAllInlineMedia":false,"friendsCount":4142,"createdAt":"Feb 9, 2009 7:03:22 PM","favouritesCount":42,"utcOffset":7200,"timeZone":"Pretoria","profileBackgroundImageUrl":"http://pbs.twimg.com/profile_background_images/537107494/EWN_Twitter_BG.jpg","profileBackgroundImageUrlHttps":"https://pbs.twimg.com/profile_background_images/537107494/EWN_Twitter_BG.jpg","profileBannerImageUrl":"https://pbs.twimg.com/profile_banners/20433284/1464855368","profileBackgroundTiled":false,"lang":"en","statusesCount":172783,"isGeoEnabled":true,"isVerified":false,"translator":false,"listedCount":1642,"isFollowRequestSent":false},{"_id":{"timestamp":1469855734,"machineIdentifier":1136930,"processIdentifier":9999,"counter":12750608},"id":137916402,"name":"Últimas","screenName":"paguitoportal","location":"México, DF","description":"http://Paguito.com Portal Noticias México, Videos de Música Finanzas Computo Espectáculos Deportes","descriptionURLEntities":[],"isContributorsEnabled":false,"profileImageUrl":"http://pbs.twimg.com/profile_images/3311019011/6529dab6fde3365affbc5de144366f69_normal.jpeg","profileImageUrlHttps":"https://pbs.twimg.com/profile_images/3311019011/6529dab6fde3365affbc5de144366f69_normal.jpeg","isDefaultProfileImage":false,"url":"http://www.paguito.com/portal/","isProtected":false,"followersCount":10210,"profileBackgroundColor":"B2DFDA","profileTextColor":"333333","profileLinkColor":"93A644","profileSidebarFillColor":"F3F3F3","profileSidebarBorderColor":"FFFFFF","profileUseBackgroundImage":true,"isDefaultProfile":false,"showAllInlineMedia":false,"friendsCount":7599,"createdAt":"Apr 28, 2010 9:43:49 AM","favouritesCount":4642,"utcOffset":-18000,"timeZone":"Mexico City","profileBackgroundImageUrl":"http://pbs.twimg.com/profile_background_images/573155461614059520/jNb4rlED.jpeg","profileBackgroundImageUrlHttps":"https://pbs.twimg.com/profile_background_images/573155461614059520/jNb4rlED.jpeg","profileBackgroundTiled":true,"lang":"es","statusesCount":530529,"isGeoEnabled":true,"isVerified":false,"translator":false,"listedCount":115,"isFollowRequestSent":false},{"_id":{"timestamp":1469855734,"machineIdentifier":1136930,"processIdentifier":9999,"counter":12750611},"id":240649814,"name":"TIMES NOW","screenName":"TimesNow","location":"India","description":"Times Now is India’s most watched English news channel. Follow us for breaking news \u0026 updates.","descriptionURLEntities":[],"isContributorsEnabled":false,"profileImageUrl":"http://pbs.twimg.com/profile_images/548508720888442881/T4tYT9xR_normal.jpeg","profileImageUrlHttps":"https://pbs.twimg.com/profile_images/548508720888442881/T4tYT9xR_normal.jpeg","isDefaultProfileImage":false,"url":"http://www.timesnow.tv","isProtected":false,"followersCount":4957160,"profileBackgroundColor":"C0DEED","profileTextColor":"333333","profileLinkColor":"3B94D9","profileSidebarFillColor":"DDEEF6","profileSidebarBorderColor":"FFFFFF","profileUseBackgroundImage":true,"isDefaultProfile":false,"showAllInlineMedia":false,"friendsCount":235,"createdAt":"Jan 20, 2011 6:17:23 PM","favouritesCount":1,"utcOffset":19800,"timeZone":"New Delhi","profileBackgroundImageUrl":"http://pbs.twimg.com/profile_background_images/818423800/453b0dbec01f76277e7d3efa46e4c5ea.jpeg","profileBackgroundImageUrlHttps":"https://pbs.twimg.com/profile_background_images/818423800/453b0dbec01f76277e7d3efa46e4c5ea.jpeg","profileBannerImageUrl":"https://pbs.twimg.com/profile_banners/240649814/1467213904","profileBackgroundTiled":false,"lang":"en","statusesCount":153327,"isGeoEnabled":true,"isVerified":true,"translator":false,"listedCount":3403,"isFollowRequestSent":false},{"_id":{"timestamp":1469855734,"machineIdentifier":1136930,"processIdentifier":9999,"counter":12750613},"id":5781452,"name":"el ¡Soopèr! ن","screenName":"SooperMexican","location":"North East Coast","description":"SOOPer. Mexy. Conservative. TeaPartier, cartoonist, studied in theology, math \u0026 philosophy. I made Thomas Sowell laugh. Señor Fellow at LatinoCon Foundation.","descriptionURLEntities":[],"isContributorsEnabled":false,"profileImageUrl":"http://pbs.twimg.com/profile_images/561225650665566210/7gbUsBjB_normal.jpeg","profileImageUrlHttps":"https://pbs.twimg.com/profile_images/561225650665566210/7gbUsBjB_normal.jpeg","isDefaultProfileImage":false,"url":"http://www.soopermexican.com","isProtected":false,"followersCount":52996,"profileBackgroundColor":"FFFFFF","profileTextColor":"666666","profileLinkColor":"32393B","profileSidebarFillColor":"FFFFFF","profileSidebarBorderColor":"FFFFFF","profileUseBackgroundImage":true,"isDefaultProfile":false,"showAllInlineMedia":false,"friendsCount":2008,"createdAt":"May 5, 2007 9:54:08 AM","favouritesCount":1524,"utcOffset":-14400,"timeZone":"Eastern Time (US \u0026 Canada)","profileBackgroundImageUrl":"http://pbs.twimg.com/profile_background_images/711097235/d60467a4093a94910e30d6000c82e3c8.jpeg","profileBackgroundImageUrlHttps":"https://pbs.twimg.com/profile_background_images/711097235/d60467a4093a94910e30d6000c82e3c8.jpeg","profileBannerImageUrl":"https://pbs.twimg.com/profile_banners/5781452/1402897708","profileBackgroundTiled":true,"lang":"en","statusesCount":190457,"isGeoEnabled":true,"isVerified":false,"translator":false,"listedCount":1805,"isFollowRequestSent":false},{"_id":{"timestamp":1469855734,"machineIdentifier":1136930,"processIdentifier":9999,"counter":12750614},"id":22585928,"name":"Richard Price","screenName":"energyme","location":"Australia","description":"Helping companies increase their profile, and showcase new products and technology in the energy industry.","descriptionURLEntities":[],"isContributorsEnabled":false,"profileImageUrl":"http://pbs.twimg.com/profile_images/468214326/eme_sm_normal.png","profileImageUrlHttps":"https://pbs.twimg.com/profile_images/468214326/eme_sm_normal.png","isDefaultProfileImage":false,"url":"http://energymenews.blogspot.com.au/","isProtected":false,"followersCount":10309,"profileBackgroundColor":"022330","profileTextColor":"333333","profileLinkColor":"0084B4","profileSidebarFillColor":"C0DFEC","profileSidebarBorderColor":"A8C7F7","profileUseBackgroundImage":true,"isDefaultProfile":false,"showAllInlineMedia":false,"friendsCount":13,"createdAt":"Mar 3, 2009 10:35:44 AM","favouritesCount":0,"utcOffset":36000,"timeZone":"Sydney","profileBackgroundImageUrl":"http://abs.twimg.com/images/themes/theme15/bg.png","profileBackgroundImageUrlHttps":"https://abs.twimg.com/images/themes/theme15/bg.png","profileBackgroundTiled":false,"lang":"en","statusesCount":71019,"isGeoEnabled":false,"isVerified":false,"translator":false,"listedCount":384,"isFollowRequestSent":false},{"_id":{"timestamp":1469855734,"machineIdentifier":1136930,"processIdentifier":9999,"counter":12750617},"id":759251,"name":"CNN","screenName":"CNN","description":"It’s our job to #GoThere and tell the most difficult stories. Come with us!","descriptionURLEntities":[],"isContributorsEnabled":false,"profileImageUrl":"http://pbs.twimg.com/profile_images/508960761826131968/LnvhR8ED_normal.png","profileImageUrlHttps":"https://pbs.twimg.com/profile_images/508960761826131968/LnvhR8ED_normal.png","isDefaultProfileImage":false,"url":"http://www.cnn.com","isProtected":false,"followersCount":26090054,"profileBackgroundColor":"323232","profileTextColor":"000000","profileLinkColor":"004287","profileSidebarFillColor":"EEEEEE","profileSidebarBorderColor":"000000","profileUseBackgroundImage":false,"isDefaultProfile":false,"showAllInlineMedia":false,"friendsCount":1119,"createdAt":"Feb 9, 2007 6:35:02 AM","favouritesCount":1398,"utcOffset":-14400,"timeZone":"Eastern Time (US \u0026 Canada)","profileBackgroundImageUrl":"http://pbs.twimg.com/profile_background_images/515228058286952449/zVfUxqPl.jpeg","profileBackgroundImageUrlHttps":"https://pbs.twimg.com/profile_background_images/515228058286952449/zVfUxqPl.jpeg","profileBannerImageUrl":"https://pbs.twimg.com/profile_banners/759251/1454562486","profileBackgroundTiled":false,"lang":"en","statusesCount":90125,"isGeoEnabled":true,"isVerified":true,"translator":false,"listedCount":116432,"isFollowRequestSent":false},{"_id":{"timestamp":1469855734,"machineIdentifier":1136930,"processIdentifier":9999,"counter":12750621},"id":142379064,"name":"ॐ भारत ॐ","screenName":"dharam_vj","location":" हिन्दू राष्ट्र भारत ","description":"धृति: क्षमा दमोऽस्‍तेयं शौचमिन्‍द्रियनिग्रह: । धीर्विद्या सत्‍यमक्रोधो दशकं धर्मलक्षणम्‌ ।। || धर्मो रक्षति रक्षितः || महर्षी रामदेव का परमभक्त |","descriptionURLEntities":[],"isContributorsEnabled":false,"profileImageUrl":"http://pbs.twimg.com/profile_images/716033652812029952/BTOs4GEr_normal.jpg","profileImageUrlHttps":"https://pbs.twimg.com/profile_images/716033652812029952/BTOs4GEr_normal.jpg","isDefaultProfileImage":false,"url":"http://bharatswabhiman.com","isProtected":false,"followersCount":14773,"profileBackgroundColor":"8B542B","profileTextColor":"333333","profileLinkColor":"9D582E","profileSidebarFillColor":"EADEAA","profileSidebarBorderColor":"D9B17E","profileUseBackgroundImage":true,"isDefaultProfile":false,"showAllInlineMedia":false,"friendsCount":3986,"createdAt":"May 11, 2010 12:41:24 AM","favouritesCount":10976,"utcOffset":19800,"timeZone":"Mumbai","profileBackgroundImageUrl":"http://abs.twimg.com/images/themes/theme8/bg.gif","profileBackgroundImageUrlHttps":"https://abs.twimg.com/images/themes/theme8/bg.gif","profileBannerImageUrl":"https://pbs.twimg.com/profile_banners/142379064/1445188553","profileBackgroundTiled":false,"lang":"en","statusesCount":261961,"isGeoEnabled":true,"isVerified":false,"translator":false,"listedCount":234,"isFollowRequestSent":false},{"_id":{"timestamp":1469855734,"machineIdentifier":1136930,"processIdentifier":9999,"counter":12750622},"id":714947334,"name":"MarieTweets☕️","screenName":"mkues65","location":"America ","description":"Independent, Pro-Trump, college graduate, taxpayer, Mother, Wife, God Bless our Military","descriptionURLEntities":[],"isContributorsEnabled":false,"profileImageUrl":"http://pbs.twimg.com/profile_images/700549477828993024/JYIv0D53_normal.png","profileImageUrlHttps":"https://pbs.twimg.com/profile_images/700549477828993024/JYIv0D53_normal.png","isDefaultProfileImage":false,"isProtected":false,"followersCount":13779,"profileBackgroundColor":"030103","profileTextColor":"D60000","profileLinkColor":"DB143C","profileSidebarFillColor":"1C1939","profileSidebarBorderColor":"FFFFFF","profileUseBackgroundImage":true,"isDefaultProfile":false,"showAllInlineMedia":false,"friendsCount":8059,"createdAt":"Jul 25, 2012 3:21:14 AM","favouritesCount":256281,"utcOffset":-10800,"timeZone":"Atlantic Time (Canada)","profileBackgroundImageUrl":"http://pbs.twimg.com/profile_background_images/378800000032304802/211752a14d2580eaf24ba29051d7910a.png","profileBackgroundImageUrlHttps":"https://pbs.twimg.com/profile_background_images/378800000032304802/211752a14d2580eaf24ba29051d7910a.png","profileBannerImageUrl":"https://pbs.twimg.com/profile_banners/714947334/1466367949","profileBackgroundTiled":true,"lang":"en","statusesCount":302398,"isGeoEnabled":false,"isVerified":false,"translator":false,"listedCount":518,"isFollowRequestSent":false},{"_id":{"timestamp":1469855734,"machineIdentifier":1136930,"processIdentifier":9999,"counter":12750623},"id":1953669344,"name":"Gâvur","screenName":"ateisthafiz","description":"Yıldız tozu, konuşan hayvan, mürted. Domuz, ayı, fare, köpek, maymun ve bitkiler ile akraba. \u0027Ben senden daha dinsizim\u0027 diye birbirini öldüren ateist gördün mü?","descriptionURLEntities":[],"isContributorsEnabled":false,"profileImageUrl":"http://pbs.twimg.com/profile_images/566069602074263552/YBxiQ_Pr_normal.jpeg","profileImageUrlHttps":"https://pbs.twimg.com/profile_images/566069602074263552/YBxiQ_Pr_normal.jpeg","isDefaultProfileImage":false,"isProtected":false,"followersCount":62393,"profileBackgroundColor":"C0DEED","profileTextColor":"333333","profileLinkColor":"0084B4","profileSidebarFillColor":"DDEEF6","profileSidebarBorderColor":"C0DEED","profileUseBackgroundImage":true,"isDefaultProfile":true,"showAllInlineMedia":false,"friendsCount":267,"createdAt":"Oct 11, 2013 2:44:43 PM","favouritesCount":4030,"utcOffset":10800,"timeZone":"Athens","profileBackgroundImageUrl":"http://abs.twimg.com/images/themes/theme1/bg.png","profileBackgroundImageUrlHttps":"https://abs.twimg.com/images/themes/theme1/bg.png","profileBannerImageUrl":"https://pbs.twimg.com/profile_banners/1953669344/1411110565","profileBackgroundTiled":false,"lang":"en","statusesCount":24268,"isGeoEnabled":false,"isVerified":false,"translator":false,"listedCount":139,"isFollowRequestSent":false},{"_id":{"timestamp":1469855734,"machineIdentifier":1136930,"processIdentifier":9999,"counter":12750626},"id":119401590,"name":"DonAlex","screenName":"DonAle_CL","location":"Chile","description":"Tuitero promedio con todo lo que eso conlleva. Dog \u0026 turtle lover. No entro por la vista.","descriptionURLEntities":[],"isContributorsEnabled":false,"profileImageUrl":"http://pbs.twimg.com/profile_images/735251455595163650/FDdyJItU_normal.jpg","profileImageUrlHttps":"https://pbs.twimg.com/profile_images/735251455595163650/FDdyJItU_normal.jpg","isDefaultProfileImage":false,"url":"http://www.google.cl","isProtected":false,"followersCount":1848,"profileBackgroundColor":"000000","profileTextColor":"000000","profileLinkColor":"91D2FA","profileSidebarFillColor":"000000","profileSidebarBorderColor":"000000","profileUseBackgroundImage":true,"isDefaultProfile":false,"showAllInlineMedia":false,"friendsCount":1390,"createdAt":"Mar 3, 2010 8:49:58 PM","favouritesCount":27571,"utcOffset":-10800,"timeZone":"Santiago","profileBackgroundImageUrl":"http://pbs.twimg.com/profile_background_images/630765350590763008/c9jnDOV7.jpg","profileBackgroundImageUrlHttps":"https://pbs.twimg.com/profile_background_images/630765350590763008/c9jnDOV7.jpg","profileBannerImageUrl":"https://pbs.twimg.com/profile_banners/119401590/1464132739","profileBackgroundTiled":false,"lang":"es","statusesCount":88127,"isGeoEnabled":true,"isVerified":false,"translator":false,"listedCount":18,"isFollowRequestSent":false}]
